pyenvs/__init__.py
pyenvs/env_loader.py
pyenvs-0.0.2.dist-info/LICENSE
pyenvs-0.0.2.dist-info/METADATA
pyenvs-0.0.2.dist-info/WHEEL
pyenvs-0.0.2.dist-info/top_level.txt
pyenvs-0.0.2.dist-info/RECORD
